README.rst
setup.py
kylin_client/__init__.py
kylin_client/kylin_client.py
kylin_client.egg-info/PKG-INFO
kylin_client.egg-info/SOURCES.txt
kylin_client.egg-info/dependency_links.txt
kylin_client.egg-info/requires.txt
kylin_client.egg-info/top_level.txt