Metadata-Version: 1.1
Name: kylin-client
Version: 1.0.2
Summary: kylin api client
Home-page: UNKNOWN
Author: chenglei
Author-email: mechenglei@163.com
License: BSD License
Platform: win7
Platform: linux
Classifier: Development Status :: 4 - Beta
Classifier: Operating System :: OS Independent
Classifier: Intended Audience :: Developers
Classifier: License :: OSI Approved :: BSD License
Classifier: Programming Language :: Python
Classifier: Programming Language :: Python :: Implementation
Classifier: Programming Language :: Python :: 2.7
Classifier: Topic :: Software Development :: Libraries
